ms_imputedhours_core/__init__.py
ms_imputedhours_core/agreements/__init__.py
ms_imputedhours_core/agreements/__tests__/__init__.py
ms_imputedhours_core/agreements/__tests__/test_agreements.py
ms_imputedhours_core/employee/__init__.py
ms_imputedhours_core/employee/__tests__/__init__.py
ms_imputedhours_core/employee/__tests__/test_employee.py
ms_imputedhours_core/employee/data/__init__.py
ms_imputedhours_core/employee/data/__tests__/__init__.py
ms_imputedhours_core/employee/data/__tests__/test_capacity.py
ms_imputedhours_core/employee/data/__tests__/test_data.py
ms_imputedhours_core/employee/data/bigquery.py
ms_imputedhours_core/employee/data/constants.py
ms_imputedhours_core/employee/data/helpers/__init__.py
ms_imputedhours_core/employee/data/helpers/__tests__/__init__.py
ms_imputedhours_core/employee/data/helpers/__tests__/test_alert.py
ms_imputedhours_core/employee/data/helpers/__tests__/test_bigquery.py
ms_imputedhours_core/employee/data/helpers/__tests__/test_dates.py
ms_imputedhours_core/employee/data/helpers/alert.py
ms_imputedhours_core/employee/data/helpers/bigquery.py
ms_imputedhours_core/employee/data/helpers/dates.py
ms_imputedhours_core/employee/data/transformers/__init__.py
ms_imputedhours_core/employee/data/transformers/hours.py
ms_imputedhours_core/office/__init__.py
ms_imputedhours_core/office/__tests__/__init__.py
ms_imputedhours_core/office/__tests__/test_office.py
ms_imputedhours_core-0.5.1.dist-info/LICENSE
ms_imputedhours_core-0.5.1.dist-info/METADATA
ms_imputedhours_core-0.5.1.dist-info/WHEEL
ms_imputedhours_core-0.5.1.dist-info/RECORD
